deploy_tools/__init__.py
deploy_tools/cli.py
deploy_tools/compile.py
deploy_tools/deploy.py
deploy_tools/files.py
deploy_tools/plugin.py
deploy_tools/transact.py
contract_deploy_tools-0.11.1.dist-info/LICENSE
contract_deploy_tools-0.11.1.dist-info/METADATA
contract_deploy_tools-0.11.1.dist-info/WHEEL
contract_deploy_tools-0.11.1.dist-info/entry_points.txt
contract_deploy_tools-0.11.1.dist-info/top_level.txt
contract_deploy_tools-0.11.1.dist-info/RECORD
